gamchanger/.DS_Store
gamchanger/__init__.py
gamchanger/gamchanger.js
gamchanger/gamchanger.py
gamchanger/index.html
gamchanger/__pycache__/__init__.cpython-310.pyc
gamchanger/__pycache__/__init__.cpython-37.pyc
gamchanger/__pycache__/__init__.cpython-39.pyc
gamchanger/__pycache__/gamchanger.cpython-310.pyc
gamchanger/__pycache__/gamchanger.cpython-37.pyc
gamchanger/__pycache__/gamchanger.cpython-39.pyc
gamchanger-0.1.13.dist-info/METADATA
gamchanger-0.1.13.dist-info/WHEEL
gamchanger-0.1.13.dist-info/top_level.txt
gamchanger-0.1.13.dist-info/RECORD
