Metadata-Version: 2.1
Name: gamchanger
Version: 0.1.13
Summary: A Python package to run GAM Changer in your computation notebooks.
Home-page: https://github.com/xiaohk/gam-changer
Author: Jay Wang
Author-email: jayw@zijie.wang
License: MIT license
Keywords: gamchanger
Classifier: Development Status :: 2 - Pre-Alpha
Classifier: Intended Audience :: Developers
Classifier: License :: OSI Approved :: MIT License
Classifier: Natural Language :: English
Classifier: Programming Language :: Python :: 3
Classifier: Programming Language :: Python :: 3.6
Classifier: Programming Language :: Python :: 3.7
Classifier: Programming Language :: Python :: 3.8
Requires-Python: >=3.6
Requires-Dist: numpy
Requires-Dist: pandas
Requires-Dist: ipython
